<annotation>
	<folder>auto_images</folder>
	<filename>81n5R5K1P5n22k2p2q6rN4b1P8_f.png</filename>
	<path>C:\Users\Jack\Desktop\Github Projects\Chess\auto_images\81n5R5K1P5n22k2p2q6rN4b1P8_f.png</path>
	<source>
		<database>Unknown</database>
	</source>
	<size>
		<width>912</width>
		<height>912</height>
		<depth>3</depth>
	</size>
	<segmented>0</segmented>
	<object>
		<name>n</name>
		<pose>Unspecified</pose>
		<truncated>0</truncated>
		<difficult>0</difficult>
		<bndbox>
			<xmin>692</xmin>
			<ymin>688</ymin>
			<xmax>789</xmax>
			<ymax>791</ymax>
		</bndbox>
	</object>
	<object>
		<name>R</name>
		<pose>Unspecified</pose>
		<truncated>0</truncated>
		<difficult>0</difficult>
		<bndbox>
			<xmin>19</xmin>
			<ymin>693</ymin>
			<xmax>102</xmax>
			<ymax>790</ymax>
		</bndbox>
	</object>
	<object>
		<name>K</name>
		<pose>Unspecified</pose>
		<truncated>0</truncated>
		<difficult>0</difficult>
		<bndbox>
			<xmin>238</xmin>
			<ymin>571</ymin>
			<xmax>338</xmax>
			<ymax>679</ymax>
		</bndbox>
	</object>
	<object>
		<name>P</name>
		<pose>Unspecified</pose>
		<truncated>0</truncated>
		<difficult>0</difficult>
		<bndbox>
			<xmin>20</xmin>
			<ymin>586</ymin>
			<xmax>95</xmax>
			<ymax>677</ymax>
		</bndbox>
	</object>
	<object>
		<name>n</name>
		<pose>Unspecified</pose>
		<truncated>0</truncated>
		<difficult>0</difficult>
		<bndbox>
			<xmin>238</xmin>
			<ymin>461</ymin>
			<xmax>335</xmax>
			<ymax>564</ymax>
		</bndbox>
	</object>
	<object>
		<name>k</name>
		<pose>Unspecified</pose>
		<truncated>0</truncated>
		<difficult>0</difficult>
		<bndbox>
			<xmin>579</xmin>
			<ymin>344</ymin>
			<xmax>679</xmax>
			<ymax>452</ymax>
		</bndbox>
	</object>
	<object>
		<name>p</name>
		<pose>Unspecified</pose>
		<truncated>0</truncated>
		<difficult>0</difficult>
		<bndbox>
			<xmin>247</xmin>
			<ymin>359</ymin>
			<xmax>322</xmax>
			<ymax>450</ymax>
		</bndbox>
	</object>
	<object>
		<name>q</name>
		<pose>Unspecified</pose>
		<truncated>0</truncated>
		<difficult>0</difficult>
		<bndbox>
			<xmin>805</xmin>
			<ymin>236</ymin>
			<xmax>904</xmax>
			<ymax>335</ymax>
		</bndbox>
	</object>
	<object>
		<name>r</name>
		<pose>Unspecified</pose>
		<truncated>0</truncated>
		<difficult>0</difficult>
		<bndbox>
			<xmin>19</xmin>
			<ymin>239</ymin>
			<xmax>102</xmax>
			<ymax>336</ymax>
		</bndbox>
	</object>
	<object>
		<name>N</name>
		<pose>Unspecified</pose>
		<truncated>0</truncated>
		<difficult>0</difficult>
		<bndbox>
			<xmin>806</xmin>
			<ymin>121</ymin>
			<xmax>903</xmax>
			<ymax>223</ymax>
		</bndbox>
	</object>
	<object>
		<name>b</name>
		<pose>Unspecified</pose>
		<truncated>0</truncated>
		<difficult>0</difficult>
		<bndbox>
			<xmin>244</xmin>
			<ymin>120</ymin>
			<xmax>328</xmax>
			<ymax>222</ymax>
		</bndbox>
	</object>
	<object>
		<name>P</name>
		<pose>Unspecified</pose>
		<truncated>0</truncated>
		<difficult>0</difficult>
		<bndbox>
			<xmin>20</xmin>
			<ymin>132</ymin>
			<xmax>95</xmax>
			<ymax>223</ymax>
		</bndbox>
	</object>
</annotation>
