<annotation>
	<folder>auto_images</folder>
	<filename>B2KQq24p1q1p781B1N3p87p3r1k2_f.png</filename>
	<path>C:\Users\Jack\Desktop\Github Projects\Chess\auto_images\B2KQq24p1q1p781B1N3p87p3r1k2_f.png</path>
	<source>
		<database>Unknown</database>
	</source>
	<size>
		<width>912</width>
		<height>912</height>
		<depth>3</depth>
	</size>
	<segmented>0</segmented>
	<object>
		<name>B</name>
		<pose>Unspecified</pose>
		<truncated>0</truncated>
		<difficult>0</difficult>
		<bndbox>
			<xmin>812</xmin>
			<ymin>801</ymin>
			<xmax>896</xmax>
			<ymax>904</ymax>
		</bndbox>
	</object>
	<object>
		<name>K</name>
		<pose>Unspecified</pose>
		<truncated>0</truncated>
		<difficult>0</difficult>
		<bndbox>
			<xmin>465</xmin>
			<ymin>798</ymin>
			<xmax>565</xmax>
			<ymax>906</ymax>
		</bndbox>
	</object>
	<object>
		<name>Q</name>
		<pose>Unspecified</pose>
		<truncated>0</truncated>
		<difficult>0</difficult>
		<bndbox>
			<xmin>351</xmin>
			<ymin>804</ymin>
			<xmax>450</xmax>
			<ymax>903</ymax>
		</bndbox>
	</object>
	<object>
		<name>q</name>
		<pose>Unspecified</pose>
		<truncated>0</truncated>
		<difficult>0</difficult>
		<bndbox>
			<xmin>237</xmin>
			<ymin>804</ymin>
			<xmax>336</xmax>
			<ymax>903</ymax>
		</bndbox>
	</object>
	<object>
		<name>p</name>
		<pose>Unspecified</pose>
		<truncated>0</truncated>
		<difficult>0</difficult>
		<bndbox>
			<xmin>361</xmin>
			<ymin>700</ymin>
			<xmax>435</xmax>
			<ymax>791</ymax>
		</bndbox>
	</object>
	<object>
		<name>q</name>
		<pose>Unspecified</pose>
		<truncated>0</truncated>
		<difficult>0</difficult>
		<bndbox>
			<xmin>124</xmin>
			<ymin>690</ymin>
			<xmax>223</xmax>
			<ymax>789</ymax>
		</bndbox>
	</object>
	<object>
		<name>p</name>
		<pose>Unspecified</pose>
		<truncated>0</truncated>
		<difficult>0</difficult>
		<bndbox>
			<xmin>815</xmin>
			<ymin>586</ymin>
			<xmax>889</xmax>
			<ymax>677</ymax>
		</bndbox>
	</object>
	<object>
		<name>B</name>
		<pose>Unspecified</pose>
		<truncated>0</truncated>
		<difficult>0</difficult>
		<bndbox>
			<xmin>698</xmin>
			<ymin>347</ymin>
			<xmax>782</xmax>
			<ymax>449</ymax>
		</bndbox>
	</object>
	<object>
		<name>N</name>
		<pose>Unspecified</pose>
		<truncated>0</truncated>
		<difficult>0</difficult>
		<bndbox>
			<xmin>465</xmin>
			<ymin>348</ymin>
			<xmax>562</xmax>
			<ymax>450</ymax>
		</bndbox>
	</object>
	<object>
		<name>p</name>
		<pose>Unspecified</pose>
		<truncated>0</truncated>
		<difficult>0</difficult>
		<bndbox>
			<xmin>20</xmin>
			<ymin>359</ymin>
			<xmax>95</xmax>
			<ymax>450</ymax>
		</bndbox>
	</object>
	<object>
		<name>p</name>
		<pose>Unspecified</pose>
		<truncated>0</truncated>
		<difficult>0</difficult>
		<bndbox>
			<xmin>20</xmin>
			<ymin>132</ymin>
			<xmax>95</xmax>
			<ymax>223</ymax>
		</bndbox>
	</object>
	<object>
		<name>r</name>
		<pose>Unspecified</pose>
		<truncated>0</truncated>
		<difficult>0</difficult>
		<bndbox>
			<xmin>473</xmin>
			<ymin>12</ymin>
			<xmax>556</xmax>
			<ymax>109</ymax>
		</bndbox>
	</object>
	<object>
		<name>k</name>
		<pose>Unspecified</pose>
		<truncated>0</truncated>
		<difficult>0</difficult>
		<bndbox>
			<xmin>238</xmin>
			<ymin>4</ymin>
			<xmax>338</xmax>
			<ymax>112</ymax>
		</bndbox>
	</object>
</annotation>
